message_service/__init__.py
message_service/main.py
devops_message_service_project_2022-1.3.0.dist-info/METADATA
devops_message_service_project_2022-1.3.0.dist-info/WHEEL
devops_message_service_project_2022-1.3.0.dist-info/top_level.txt
devops_message_service_project_2022-1.3.0.dist-info/RECORD
