Metadata-Version: 2.1
Name: devops-message-service-project-2022
Version: 1.3.0
Summary: UNKNOWN
Home-page: UNKNOWN
License: UNKNOWN
Platform: UNKNOWN
Requires-Dist: fastapi
Requires-Dist: fastapi-contrib
Requires-Dist: sqlalchemy
Requires-Dist: uvicorn
Requires-Dist: psycopg2-binary
Requires-Dist: kafka-python
Requires-Dist: websockets
Requires-Dist: python-engineio (==3.13.0)
Requires-Dist: python-socketio (==4.6.1)
Requires-Dist: jaeger-client
Requires-Dist: opentracing
Requires-Dist: prometheus-fastapi-instrumentator
